[
  {
    "Title": "Keroué + Oni Kira",
    "DateString": "2026-01-31T00:00:00.0000000",
    "Url": "https://www.abconcerts.be/en/agenda/keroue/a10Qw000006PJX7IAO",
    "ImageUrl": "https://d12xfkzf9kx8ij.cloudfront.net/a0KQw00000Hes6LMAR_1240x720.jpg",
    "Location": "AB Concerts, Brussel",
    "Description": "French rap with technique and charismatic presence"
  },
  {
    "Title": "Thylacine + KOWARI",
    "DateString": "2026-01-31T00:00:00.0000000",
    "Url": "https://www.abconcerts.be/en/agenda/thylacine/a10Qw000001cKmkIAE",
    "ImageUrl": "https://d12xfkzf9kx8ij.cloudfront.net/a0KQw00000Em4PRMAZ_1240x720.jpg",
    "Location": "AB Concerts, Brussel",
    "Description": "A new musical odyssey for a unique artist"
  }
]